mdformat_toc/__init__.py
mdformat_toc/_heading.py
mdformat_toc/_options.py
mdformat_toc/_tokens.py
mdformat_toc/plugin.py
mdformat_toc/slug.py
mdformat_toc-0.5.0.dist-info/METADATA
mdformat_toc-0.5.0.dist-info/WHEEL
mdformat_toc-0.5.0.dist-info/entry_points.txt
mdformat_toc-0.5.0.dist-info/licenses/LICENSE
mdformat_toc-0.5.0.dist-info/RECORD
