Metadata-Version: 2.4
Name: mdformat-toc
Version: 0.5.0
Summary: Mdformat plugin to generate table of contents
License: MIT
License-File: LICENSE
Keywords: mdformat,markdown,commonmark,formatter
Author: Taneli Hukkinen
Author-email: hukkin@users.noreply.github.com
Requires-Python: >=3.9
Classifier: License :: OSI Approved :: MIT License
Classifier: Programming Language :: Python :: 3
Classifier: Programming Language :: Python :: 3.9
Classifier: Programming Language :: Python :: 3.10
Classifier: Programming Language :: Python :: 3.11
Classifier: Programming Language :: Python :: 3.12
Classifier: Programming Language :: Python :: 3.13
Classifier: Programming Language :: Python :: 3.14
Classifier: Topic :: Documentation
Classifier: Topic :: Text Processing :: Markup
Classifier: Typing :: Typed
Requires-Dist: mdformat (>=0.7.5)
Project-URL: Repository, https://github.com/hukkin/mdformat-toc
